README
setup.py
scripts/sslsnoop
scripts/sslsnoop-openssh
scripts/sslsnoop-openssh-dump
scripts/sslsnoop-openssl
sslsnoop/__init__.py
sslsnoop/cleaner.py
sslsnoop/ctypes_nss.py
sslsnoop/ctypes_nss_generated.py
sslsnoop/ctypes_openssh.py
sslsnoop/ctypes_openssl.py
sslsnoop/ctypes_openssl_generated.py
sslsnoop/ctypes_putty.py
sslsnoop/ctypes_putty_cryptoapi_generated.py
sslsnoop/ctypes_putty_generated.py
sslsnoop/engine.py
sslsnoop/finder.py
sslsnoop/generate.py
sslsnoop/lrucache.py
sslsnoop/network.py
sslsnoop/openssh.py
sslsnoop/openssl.py
sslsnoop/openvpn.py
sslsnoop/output.py
sslsnoop/paramiko_packet.py
sslsnoop/preprocess.py
sslsnoop/stream.py
sslsnoop/test-scapy.py
sslsnoop/test.py
sslsnoop/utils.py
sslsnoop.egg-info/PKG-INFO
sslsnoop.egg-info/SOURCES.txt
sslsnoop.egg-info/dependency_links.txt
sslsnoop.egg-info/requires.txt
sslsnoop.egg-info/top_level.txt