Metadata-Version: 1.0
Name: sslsnoop
Version: 0.11
Summary: Dumps the live traffic of an ssl-encrypted stream.
Home-page: http://packages.python.org/sslsnoop/
Author: Loic Jaquemet
Author-email: loic.jaquemet+python@gmail.com
License: GPL
Download-URL: http://github.com/trolldbois/sslsnoop/tree/master
Keywords: memory,analysis,forensics,struct,ptrace,openssh,openssl,decrypt
Platform: UNKNOWN
Classifier: Topic :: System :: Networking
Classifier: Topic :: Security
Classifier: Environment :: Console
Classifier: Intended Audience :: Developers
Classifier: License :: OSI Approved :: GNU General Public License (GPL)
Classifier: Programming Language :: Python
Classifier: Development Status :: 5 - Production/Stable
